fieldclimate/__init__.py
fieldclimate/clean.py
fieldclimate/django.py
python_fieldclimate-1.3.dist-info/AUTHORS.rst
python_fieldclimate-1.3.dist-info/LICENSE
python_fieldclimate-1.3.dist-info/METADATA
python_fieldclimate-1.3.dist-info/WHEEL
python_fieldclimate-1.3.dist-info/top_level.txt
python_fieldclimate-1.3.dist-info/RECORD
