Metadata-Version: 2.1
Name: python-fieldclimate
Version: 1.3
Summary: A client for the iMetos FieldClimate API.
Home-page: https://github.com/agrimgt/python-fieldclimate
Author: Agrimanagement, Inc.
Author-email: pmarshall@agrimgt.com
License: MIT
Project-URL: API Documentation, https://api.fieldclimate.com/v1/docs/
Platform: UNKNOWN
Classifier: Development Status :: 5 - Production/Stable
Classifier: Framework :: AsyncIO
Classifier: Intended Audience :: Developers
Classifier: License :: OSI Approved :: MIT License
Classifier: Operating System :: OS Independent
Classifier: Programming Language :: Python
Classifier: Programming Language :: Python :: 3
Classifier: Programming Language :: Python :: 3.5
Classifier: Programming Language :: Python :: 3.6
Classifier: Programming Language :: Python :: 3.7
Classifier: Programming Language :: Python :: 3 :: Only
Requires-Python: >=3.6
Requires-Dist: asks
Requires-Dist: pycryptodome
